<?xml version="1.0" encoding="utf-8"?>
<XnaContent xmlns:Generic="System.Collections.Generic">
  <Asset Type="Dictionary[string, string]">
    <Item>
      <Key>0</Key>
      <Value>[Name:FoodConfirm][Text:Really eat the {0}?][Selection:YesNo][Trigger:UseItem]</Value>
    </Item>
    <Item>
      <Key>1</Key>
      <Value>[Name:GiftConfirm][Text:Give {0} to {1}?][Selection:YesNo][Trigger:ConfirmGift]</Value>
    </Item>
    <Item>
      <Key>2</Key>
      <Value>[Name:ItemConfirm][Text:Use {0} on who?][Selection:Party][Trigger:UseItem]</Value>
    </Item>
    <Item>
      <Key>3</Key>
      <Value>[Name:ClassItemConfirm][Text:Really use the {0}?][Selection:YesNo][Trigger:UseItem]</Value>
    </Item>
    <Item>
      <Key>4</Key>
      <Value>[Name:AdventurerTree][Text:...{{Talk-Talk|Join Party-Party}}]</Value>
    </Item>
    <Item>
      <Key>5</Key>
      <Value>[Name:Save][Text:Save and end the day?][Selection:YesNo][Trigger:EndDay]</Value>
    </Item>
    <Item>
      <Key>6</Key>
      <Value>[Name:ReallyExit][Text:Are you sure?][Selection:YesNo][Trigger:Exit]</Value>
    </Item>
    <Item>
      <Key>7</Key>
      <Value>[Name:Rune_of_Return_Use][Text:Use the {0} to the dungeon entrance?][Selection:YesNo][Trigger:UseItem]</Value>
    </Item>
    <Item>
      <Key>8</Key>
      <Value>[Name:Rune_of_Return_Empty][Text:The {0}'s energy is spent.]</Value>
    </Item>
    <Item>
      <Key>9</Key>
      <Value>[Name:Rune_of_Return_No_Dungeon][Text:The rune cannot work here.]</Value>
    </Item>
    <Item>
      <Key>10</Key>
      <Value>[Name:Key_Door][Text:The door is locked. You will need a key to open it.]</Value>
    </Item>
    <Item>
      <Key>11</Key>
      <Value>[Name:Item_Door][Text:A strangely shaped keyhole is embedded in the door {{Attempt to Open-OpenDoor|Never Mind-Cancel}}]</Value>
    </Item>
    <Item>
      <Key>12</Key>
      <Value>[Name:Item_Door_Ope][Text:As you place the item into the keyhole, it vanishes, becoming one with the door!]</Value>
    </Item>
    <Item>
      <Key>13</Key>
      <Value>[Name:Item_Door_Close][Text:No matter how hard you try, it seems like that item won't fit here.]</Value>
    </Item>
    <Item>
      <Key>14</Key>
      <Value>[Name:Trigger_Door][Text:You see no visible means of opening this door. There must be a hidden switch or something.]</Value>
    </Item>
    <Item>
      <Key>15</Key>
      <Value>[Name:MonsterFood_Confirm][Text:Set out the {0} here?][Selection:YesNo][Trigger:UseItem]</Value>
    </Item>
    <Item>
      <Key>16</Key>
      <Value>[Name:MonsterFood_Yes][Text:You place the {0} on the ground.]</Value>
    </Item>
    <Item>
      <Key>17</Key>
      <Value>[Name:MonsterFood_False][Text:You see no monster tracks here, better use it somewhere else.]</Value>
    </Item>
    <Item>
      <Key>18</Key>
      <Value>[Name:MonsterFood_Duplicate][Text:Tantalizing food has already been placed.]</Value>
    </Item>
    <Item>
      <Key>19</Key>
      <Value>[Name:Pedestal_Ruby][Text:A shining red gem.]</Value>
    </Item>
    <Item>
      <Key>20</Key>
      <Value>[Name:Pedestal_Emerald][Text:A shining red gem.]</Value>
    </Item>
    <Item>
      <Key>21</Key>
      <Value>[Name:Defeat][Text:You have been defeated.]</Value>
    </Item>
    <Item>
      <Key>22</Key>
      <Value>[Name:New_Villager][Text:A New Villager has arrived in town.]</Value>
    </Item>
    <Item>
      <Key>23</Key>
      <Value>[Name:New_Villagers][Text:New Villagers have arrived in town.]</Value>
    </Item>
    <Item>
      <Key>24</Key>
      <Value>[Name:Upgrade 1][Text:Tavern/A place where people can gather]</Value>
    </Item>
    <Item>
      <Key>25</Key>
      <Value>[Name:Selection_Talk][Text:Talk][TextVerb:Talk]</Value>
    </Item>
    <Item>
      <Key>26</Key>
      <Value>[Name:Selection_Gift][Text:Gift][TextVerb:Gift]</Value>
    </Item>
    <Item>
      <Key>27</Key>
      <Value>[Name:Selection_Party][Text:Join Party][TextVerb:Party]</Value>
    </Item>
    <Item>
      <Key>28</Key>
      <Value>[Name:Selection_NeverMind][Text:Never Mind][TextVerb:Cancel]</Value>
    </Item>
    <Item>
      <Key>29</Key>
      <Value>[Name:Selection_ShipGoods][Text:Ship Goods][TextVerb:ShipGoods]</Value>
    </Item>
    <Item>
      <Key>30</Key>
      <Value>[Name:Selection_Yes][Text:Yes][TextVerb:Yes]</Value>
    </Item>
    <Item>
      <Key>31</Key>
      <Value>[Name:Selection_No][Text:No][TextVerb:Cancel]</Value>
    </Item>
    <Item>
      <Key>32</Key>
      <Value>[Name:Selection_Buy][Text:Buy Items][TextVerb:Buy]</Value>
    </Item>
    <Item>
      <Key>33</Key>
      <Value>[Name:Selection_Requests][Text:Show Requests][TextVerb:ShowRequests]</Value>
    </Item>
    <Item>
      <Key>34</Key>
      <Value>[Name:PetFollow][Text:Have {0} follow you?][Selection:YesNo][Trigger:PetFollow]</Value>
    </Item>
    <Item>
      <Key>35</Key>
      <Value>[Name:PetUnfollow][Text:Leave {0} here?][Selection:YesNo][Trigger:PetUnfollow]</Value>
    </Item>
    <Item>
      <Key>36</Key>
      <Value>[Name:Selection_Propose][Text:Propose][TextVerb:Propose]</Value>
    </Item>
    <Item>
      <Key>37</Key>
      <Value>[Name:Selection_Date][Text:Ask to Date][TextVerb:Date]</Value>
    </Item>
    <Item>
      <Key>38</Key>
      <Value>[Name:Read_Book][Text:Read {0}?][Selection:YesNo][Trigger:UseItem]</Value>
    </Item>
	<Item>
      <Key>39</Key>
      <Value>[Name:Wrong_Tool][Text:Wrong Tool!]</Value>
    </Item>
	<Item>
      <Key>40</Key>
      <Value>[Name:Weak_Tool][Text:Your tool isn't strong enough!]</Value>
    </Item>
	<Item>
      <Key>41</Key>
      <Value>[Name:BuyMerch_Confirm][Text:Purchase {0} for {1}?][Selection:YesNo][Trigger:ConfirmPurchase]</Value>
    </Item>
	<Item>
      <Key>42</Key>
      <Value>[Name:BuyMerch_NoShopkeep][Text:There's no one here to take your money...]</Value>
    </Item>
	<Item>
      <Key>43</Key>
      <Value>[Name:BuyMerch_NoMoney][Text:You can't afford that.]</Value>
    </Item>
	<Item>
      <Key>44</Key>
      <Value>[Name:Desc_Agility][Text:Agilty \n Increases the damage of speed based characters.]</Value>
    </Item>
	<Item>
      <Key>45</Key>
      <Value>[Name:Desc_Damage][Text:Damage]</Value>
    </Item>
	<Item>
      <Key>46</Key>
      <Value>[Name:Desc_Defence][Text:Defence \n Reduces the damage taken by physical attacks.]</Value>
    </Item>
	<Item>
      <Key>47</Key>
      <Value>[Name:Desc_Evasion][Text:Evasion \n Increases your chance to avoid being hit.]</Value>
    </Item>
	<Item>
      <Key>48</Key>
      <Value>[Name:Desc_Magic][Text:Magic \n Increases the damage of magical characters.]</Value>
    </Item>
	<Item>
      <Key>49</Key>
      <Value>[Name:Desc_Vitality][Vitality \n Increases your maximum hit points.]</Value>
    </Item>
	<Item>
      <Key>50</Key>
      <Value>[Name:Desc_Resistance][Text:Resistance \n Reduces the damage taken by magical attacks.]</Value>
    </Item>
	<Item>
      <Key>51</Key>
      <Value>[Name:Desc_Speed][Text:Speed \n Increases your chance of going higher in the turn order.</Value>
    </Item>
	<Item>
      <Key>52</Key>
      <Value>[Name:Desc_Strength][Text:Strength \n Increases the damage of strength based characters.]</Value>
    </Item>
	<Item>
      <Key>53</Key>
      <Value>[Name:Day_End][Text:Day {0}, of {1}]</Value>
    </Item>
	<Item>
      <Key>54</Key>
      <Value>[Name:Combat_Label_Items][Text:Found Items]</Value>
    </Item>
	<Item>
      <Key>55</Key>
      <Value>[Name:Label_Town][Text:Town Name]</Value>
    </Item>
	<Item>
      <Key>56</Key>
      <Value>[Name:Label_Body][Text:Body]</Value>
    </Item>
	<Item>
      <Key>57</Key>
      <Value>[Name:Label_Hair][Text:Hair]</Value>
    </Item>
	<Item>
      <Key>58</Key>
      <Value>[Name:Label_Eyes][Text:Eyes]</Value>
    </Item>
	<Item>
      <Key>59</Key>
      <Value>[Name:Label_Shirt][Text:Shirt]</Value>
    </Item>
	<Item>
      <Key>60</Key>
      <Value>[Name:Label_Pants][Text:Pants]</Value>
    </Item>
	<Item>
      <Key>61</Key>
      <Value>[Name:Label_Shoes][Text:Shoes]</Value>
    </Item>
	<Item>
      <Key>62</Key>
      <Value>[Name:Label_Class][Text:Class]</Value>
    </Item>
	<Item>
      <Key>63</Key>
      <Value>[Name:Combat_Label_XP][Text:Gained {0} XP]</Value>
    </Item>
	<Item>
      <Key>64</Key>
      <Value>[Name:Label_Saving_Start][Text:Saving Game...]</Value>
    </Item>
	<Item>
      <Key>65</Key>
      <Value>[Name:Label_Saving_Finished][Text:Game Saved]</Value>
    </Item>
	<Item>
      <Key>66</Key>
      <Value>[Name:BuyMerch_NoSpace][Text:Your inventory is full.]</Value>
    </Item>
  </Asset>
</XnaContent>
